{
	"Id": "Lootable_00122",
	"IsStatic": true,
	"useGravity": true,
	"randomRotation": false,
	"Position": {
		"x": 0,
		"y": 0,
		"z": 0
	},
	"Rotation": {
		"x": 0,
		"y": 0,
		"z": 0
	},
	"IsGroupPosition": false,
	"GroupPositions": [],
	"Root": "5eb3dda586f77457e162a2e6",
	"Items": [
		{
			"_id": "5eb3dda586f77457e162a2e6",
			"_tpl": "578f87a3245977356274f2cb"
		},
		{
			"_id": "5eb3dda586f77457e162a2e7",
			"_tpl": "5734795124597738002c6176",
			"parentId": "5eb3dda586f77457e162a2e6",
			"slotId": "main",
			"location": {
				"x": 0,
				"y": 0,
				"r": 0
			}
		},
		{
			"_id": "5eb3dda586f77457e162a2e8",
			"_tpl": "5448ff904bdc2d6f028b456e",
			"parentId": "5eb3dda586f77457e162a2e6",
			"slotId": "main",
			"location": {
				"x": 1,
				"y": 0,
				"r": 0
			}
		},
		{
			"_id": "5eb3dda586f77457e162a2e9",
			"_tpl": "5734795124597738002c6176",
			"parentId": "5eb3dda586f77457e162a2e6",
			"slotId": "main",
			"location": {
				"x": 2,
				"y": 0,
				"r": 0
			}
		}
	]
}