{
	"Id": "loot_mod_true (128)6554258",
	"IsStatic": false,
	"useGravity": true,
	"randomRotation": true,
	"Position": {
		"x": -60.5239868,
		"y": -15.3,
		"z": 186.32
	},
	"Rotation": {
		"x": 0,
		"y": 0,
		"z": 0
	},
	"IsGroupPosition": false,
	"GroupPositions": [],
	"Root": "5ea2d1e686f7747a1e324b4e",
	"Items": [
		{
			"_id": "5ea2d1e686f7747a1e324b4e",
			"_tpl": "59d6272486f77466146386ff"
		},
		{
			"_id": "5ea2d1e686f7747a1e324b4f",
			"_tpl": "59e6658b86f77411d949b250",
			"parentId": "5ea2d1e686f7747a1e324b4e",
			"slotId": "cartridges",
			"upd": {
				"StackObjectsCount": 24
			}
		}
	]
}