{
	"Id": "Loot_barter[2] (49)10194410",
	"IsStatic": false,
	"useGravity": true,
	"randomRotation": false,
	"Position": {
		"x": -169.746948,
		"y": 0.408,
		"z": -87.88699
	},
	"Rotation": {
		"x": 0,
		"y": 0,
		"z": 0
	},
	"IsGroupPosition": false,
	"GroupPositions": [],
	"Root": "5ea2d20786f7740a7027a885",
	"Items": [
		{
			"_id": "5ea2d20786f7740a7027a885",
			"_tpl": "57372ebf2459776862260582"
		},
		{
			"_id": "5ea2d20786f7740a7027a886",
			"_tpl": "56dff3afd2720bba668b4567",
			"parentId": "5ea2d20786f7740a7027a885",
			"slotId": "cartridges",
			"upd": {
				"StackObjectsCount": 30
			}
		}
	]
}