{
	"Id": "loot_mod_true (4)6551104",
	"IsStatic": false,
	"useGravity": true,
	"randomRotation": true,
	"Position": {
		"x": -162.294,
		"y": -8.209404,
		"z": 72.4260254
	},
	"Rotation": {
		"x": 0,
		"y": 0,
		"z": 0
	},
	"IsGroupPosition": false,
	"GroupPositions": [],
	"Root": "5ea2d21586f7741183618bfb",
	"Items": [
		{
			"_id": "5ea2d21586f7741183618bfb",
			"_tpl": "5c471c442e221602b542a6f8"
		},
		{
			"_id": "5ea2d21586f7741183618bfc",
			"_tpl": "59e77a2386f7742ee578960a",
			"parentId": "5ea2d21586f7741183618bfb",
			"slotId": "cartridges",
			"upd": {
				"StackObjectsCount": 1
			}
		}
	]
}