{
	"Id": "loot_mod_common (19)6550732",
	"IsStatic": false,
	"useGravity": true,
	"randomRotation": true,
	"Position": {
		"x": -95.56598,
		"y": -5.077,
		"z": 33.3789978
	},
	"Rotation": {
		"x": 0,
		"y": 0,
		"z": 0
	},
	"IsGroupPosition": false,
	"GroupPositions": [],
	"Root": "5ea2d1ed86f77410fc4b9296",
	"Items": [
		{
			"_id": "5ea2d1ed86f77410fc4b9296",
			"_tpl": "5448c12b4bdc2d02308b456f"
		},
		{
			"_id": "5ea2d1ed86f77410fc4b9297",
			"_tpl": "57371e4124597760ff7b25f1",
			"parentId": "5ea2d1ed86f77410fc4b9296",
			"slotId": "cartridges",
			"upd": {
				"StackObjectsCount": 2
			}
		}
	]
}