{
	"Id": "Lootable_00179",
	"IsStatic": true,
	"useGravity": true,
	"randomRotation": false,
	"Position": {
		"x": 0,
		"y": 0,
		"z": 0
	},
	"Rotation": {
		"x": 0,
		"y": 0,
		"z": 0
	},
	"IsGroupPosition": false,
	"GroupPositions": [],
	"Root": "5eb3dd9e86f774116a421810",
	"Items": [
		{
			"_id": "5eb3dd9e86f774116a421810",
			"_tpl": "5909e4b686f7747f5b744fa4"
		},
		{
			"_id": "5eb3dd9f86f774116a421811",
			"_tpl": "5e2af2bc86f7746d3f3c33fc",
			"parentId": "5eb3dd9e86f774116a421810",
			"slotId": "main",
			"location": {
				"x": 0,
				"y": 0,
				"r": 0
			}
		},
		{
			"_id": "5eb3dd9f86f774116a421812",
			"_tpl": "5448c12b4bdc2d02308b456f",
			"parentId": "5eb3dd9e86f774116a421810",
			"slotId": "main",
			"location": {
				"x": 1,
				"y": 0,
				"r": 0
			}
		}
	]
}